LICENSE
README.md
setup.py
cloudmersive_cdr_api_client/__init__.py
cloudmersive_cdr_api_client/api_client.py
cloudmersive_cdr_api_client/configuration.py
cloudmersive_cdr_api_client/rest.py
cloudmersive_cdr_api_client.egg-info/PKG-INFO
cloudmersive_cdr_api_client.egg-info/SOURCES.txt
cloudmersive_cdr_api_client.egg-info/dependency_links.txt
cloudmersive_cdr_api_client.egg-info/requires.txt
cloudmersive_cdr_api_client.egg-info/top_level.txt
cloudmersive_cdr_api_client/api/__init__.py
cloudmersive_cdr_api_client/api/file_sanitization_api.py
cloudmersive_cdr_api_client/models/__init__.py
test/__init__.py
test/test_file_sanitization_api.py